mincly/__init__.py
mincly/io/__init__.py
mincly/io/ansi.py
mincly/io/common.py
mincly/io/standard.py
mincly/menu/__init__.py
mincly/py.typed
mincly/screen/__init__.py
mincly/screen/common.py
mincly/screen/confirm_screen.py
mincly/screen/input_screen.py
mincly/screen/option_screen.py
mincly-0.1.18.dist-info/LICENSE
mincly-0.1.18.dist-info/METADATA
mincly-0.1.18.dist-info/WHEEL
mincly-0.1.18.dist-info/RECORD
